IDT_lib/IDT_calculation.py
IDT_lib/__init__.py
IDT_lib/species.py
IDT_lib/thermo_real.py
IDT_lib/thermo_structure.py
IDT_lib/virial_structure.py
idtcalculation-0.0.13.dist-info/METADATA
idtcalculation-0.0.13.dist-info/WHEEL
idtcalculation-0.0.13.dist-info/top_level.txt
idtcalculation-0.0.13.dist-info/RECORD
